CHANGELOG.md
LICENSE
MANIFEST.in
README.md
requirements.txt
setup.cfg
setup.py
google_play_store/__init__.py
google_play_store/api.py
google_play_store/constants.py
google_play_store/lists.py
google_play_store/scraper.py
google_play_store/settings.py
google_play_store/utils.py
google_play_store.egg-info/PKG-INFO
google_play_store.egg-info/SOURCES.txt
google_play_store.egg-info/dependency_links.txt
google_play_store.egg-info/requires.txt
google_play_store.egg-info/top_level.txt